databunkerpro/__init__.py
databunkerpro/api.py
databunkerpro-0.1.1.dist-info/licenses/LICENSE
databunkerpro-0.1.1.dist-info/METADATA
databunkerpro-0.1.1.dist-info/WHEEL
databunkerpro-0.1.1.dist-info/top_level.txt
databunkerpro-0.1.1.dist-info/RECORD
